Topsis_Shivang_101917183/__init__.py
Topsis_Shivang_101917183/topsis.py
topsis-shivang-101917183/__init__.py
topsis-shivang-101917183/topsis.py
Topsis_Shivang_101917183-0.1.dist-info/METADATA
Topsis_Shivang_101917183-0.1.dist-info/WHEEL
Topsis_Shivang_101917183-0.1.dist-info/top_level.txt
Topsis_Shivang_101917183-0.1.dist-info/RECORD
